bunnyplot/__init__.py
bunnyplot/cli.py
bunnyplot/graph.py
bunnyplot/log.py
bunnyplot/rabbitmq.py
bunnyplot-0.1.0.dist-info/LICENSE
bunnyplot-0.1.0.dist-info/METADATA
bunnyplot-0.1.0.dist-info/WHEEL
bunnyplot-0.1.0.dist-info/entry_points.txt
bunnyplot-0.1.0.dist-info/top_level.txt
bunnyplot-0.1.0.dist-info/RECORD
