Metadata-Version: 2.1
Name: bunnyplot
Version: 0.1.0
Summary: A utility for producting GraphML from RabbitMQ
Home-page: https://github.com/jerometwell/bunnyplot
Author: Jerome Twell
Author-email: jtwell1@gmail.com
License: UNKNOWN
Platform: UNKNOWN
Classifier: Programming Language :: Python :: 3
Classifier: License :: OSI Approved :: MIT License
Classifier: Operating System :: OS Independent
Requires-Python: >=3.6
Requires-Dist: click
Requires-Dist: networkx
Requires-Dist: aiohttp
Requires-Dist: async-timeout
